shcmdmgr/__init__.py
shcmdmgr/__main__.py
shcmdmgr/cio.py
shcmdmgr/complete.py
shcmdmgr/config.py
shcmdmgr/filemanip.py
shcmdmgr/process.py
shcmdmgr/structure.py
shcmdmgr/test.py
shcmdmgr/util.py
shcmdmgr/data/_config.json
shcmdmgr/data/config_local.json
shcmdmgr/data/completion/run.py
shcmdmgr/data/completion/setup.bash
shcmdmgr/data/completion/setup.zsh
shcmdmgr-0.1.1.dist-info/LICENSE
shcmdmgr-0.1.1.dist-info/METADATA
shcmdmgr-0.1.1.dist-info/WHEEL
shcmdmgr-0.1.1.dist-info/entry_points.txt
shcmdmgr-0.1.1.dist-info/top_level.txt
shcmdmgr-0.1.1.dist-info/RECORD
