Metadata-Version: 2.1
Name: shcmdmgr
Version: 0.1.1
Summary: Tool for managing custom commands from a central location
Home-page: https://github.com/vaclavblazej/shell-command-manager
Author: Václav Blažej
Author-email: vaclavblazej@seznam.cz
License: UNKNOWN
Platform: UNKNOWN
Classifier: Development Status :: 2 - Pre-Alpha
Classifier: Intended Audience :: Developers
Classifier: Environment :: Console
Classifier: Programming Language :: Python :: 3
Classifier: License :: OSI Approved :: GNU General Public License v3 (GPLv3)
Classifier: Operating System :: POSIX :: Linux
Classifier: Topic :: Utilities
Requires-Python: >=3.8
